microdot/__init__.py
microdot/asgi.py
microdot/auth.py
microdot/cors.py
microdot/csrf.py
microdot/helpers.py
microdot/jinja.py
microdot/login.py
microdot/microdot.py
microdot/multipart.py
microdot/session.py
microdot/sse.py
microdot/test_client.py
microdot/utemplate.py
microdot/websocket.py
microdot/wsgi.py
microdot-2.5.0.dist-info/licenses/LICENSE
microdot-2.5.0.dist-info/METADATA
microdot-2.5.0.dist-info/WHEEL
microdot-2.5.0.dist-info/top_level.txt
microdot-2.5.0.dist-info/RECORD
